{
  "generatedAt": "2026-05-04T16:31:43.162222+00:00",
  "source": "Polymarket Gamma + CLOB public endpoints",
  "marketCount": 17,
  "allQualifiedCount": 51,
  "hotCount": 4,
  "total24hrVolume": 6217817.43,
  "topSignals": [
    {
      "id": "573655",
      "slug": "will-bitcoin-hit-150k-by-june-30-2026",
      "question": "Will Bitcoin hit $150k by June 30, 2026?",
      "titleZh": "比特币会在 2026 年 6 月 30 日前触及 15 万美元吗",
      "topic": "加密资产",
      "yesPrice": 0.0135,
      "noPrice": 0.9865,
      "yesPct": 1.4,
      "bestBid": 0.013,
      "bestAsk": 0.014,
      "spread": 0.001,
      "volume24hr": 5821652.894196,
      "liquidity": 19822.55555,
      "weekChangePct": 0.0,
      "score": 56.38,
      "endDate": "2026-07-01T04:00:00Z",
      "icon": "https://polymarket-upload.s3.us-east-2.amazonaws.com/BTC+fullsize.png",
      "url": "https://polymarket.com/event/will-bitcoin-hit-150k-by-june-30-2026",
      "nearBidDepth": 7873396.65,
      "nearAskDepth": 8942.68,
      "pressureLabel": "下方承接更强",
      "priceDeltaSinceLastPp": 0.0,
      "bidDepthDelta": 0.0,
      "askDepthDelta": 0.0,
      "noteZh": "该事件当前 Yes 概率约 1.4%，下方承接更强，更适合与 BTC / ETH 现货情绪一起看。"
    },
    {
      "id": "616910",
      "slug": "will-8-fed-rate-cuts-happen-in-2026",
      "question": "Will 8 Fed rate cuts happen in 2026?",
      "titleZh": "2026 年会出现 8 次美联储降息吗",
      "topic": "美联储与利率",
      "yesPrice": 0.0045,
      "noPrice": 0.9955,
      "yesPct": 0.4,
      "bestBid": 0.004,
      "bestAsk": 0.005,
      "spread": 0.001,
      "volume24hr": 55293.76924000001,
      "liquidity": 47761.57975,
      "weekChangePct": 0.1,
      "score": 49.94,
      "endDate": "2026-12-31T00:00:00Z",
      "icon": "https://polymarket-upload.s3.us-east-2.amazonaws.com/how-many-fed-rate-cuts-in-2025-9qstZkSL1dn0.jpg",
      "url": "https://polymarket.com/event/will-8-fed-rate-cuts-happen-in-2026",
      "nearBidDepth": 2864462.67,
      "nearAskDepth": 17561.84,
      "pressureLabel": "下方承接更强",
      "priceDeltaSinceLastPp": 0.0,
      "bidDepthDelta": -529.0,
      "askDepthDelta": -529.0,
      "noteZh": "该事件当前 Yes 概率约 0.4%，下方承接更强，可映射到美债、黄金和成长股方向。"
    },
    {
      "id": "616902",
      "slug": "will-no-fed-rate-cuts-happen-in-2026",
      "question": "Will no Fed rate cuts happen in 2026?",
      "titleZh": "2026 年美联储会零降息吗",
      "topic": "美联储与利率",
      "yesPrice": 0.5565,
      "noPrice": 0.4435,
      "yesPct": 55.6,
      "bestBid": 0.554,
      "bestAsk": 0.559,
      "spread": 0.005,
      "volume24hr": 29747.488552999996,
      "liquidity": 81312.60534,
      "weekChangePct": 15.15,
      "score": 45.18,
      "endDate": "2026-12-31T00:00:00Z",
      "icon": "https://polymarket-upload.s3.us-east-2.amazonaws.com/how-many-fed-rate-cuts-in-2025-9qstZkSL1dn0.jpg",
      "url": "https://polymarket.com/event/will-no-fed-rate-cuts-happen-in-2026",
      "nearBidDepth": 64673.34,
      "nearAskDepth": 38211.95,
      "pressureLabel": "下方承接更强",
      "priceDeltaSinceLastPp": 0.0,
      "bidDepthDelta": 534.67,
      "askDepthDelta": 342.19,
      "noteZh": "该事件当前 Yes 概率约 55.6%，下方承接更强，可映射到美债、黄金和成长股方向。"
    },
    {
      "id": "562802",
      "slug": "will-the-democratic-party-control-the-house-after-the-2026-midterm-elections",
      "question": "Will the Democratic Party control the House after the 2026 Midterm elections?",
      "titleZh": "2026 年中期选举后，民主党会控制众议院吗",
      "topic": "美国政治",
      "yesPrice": 0.835,
      "noPrice": 0.165,
      "yesPct": 83.5,
      "bestBid": 0.83,
      "bestAsk": 0.84,
      "spread": 0.01,
      "volume24hr": 88471.439194,
      "liquidity": 109033.6847,
      "weekChangePct": -2.0,
      "score": 42.05,
      "endDate": "2026-11-03T00:00:00Z",
      "icon": "https://polymarket-upload.s3.us-east-2.amazonaws.com/will-the-democratic-party-control-the-senate-after-the-2026-midterm-elections-JJ9h02JGR09z.png",
      "url": "https://polymarket.com/event/will-the-democratic-party-control-the-house-after-the-2026-midterm-elections",
      "nearBidDepth": 22849.95,
      "nearAskDepth": 87839.24,
      "pressureLabel": "上方卖压更重",
      "priceDeltaSinceLastPp": 0.0,
      "bidDepthDelta": 0.0,
      "askDepthDelta": 19.0,
      "noteZh": "该事件当前 Yes 概率约 83.5%，上方卖压更重，政治定价变化可能影响风险偏好。"
    },
    {
      "id": "630773",
      "slug": "will-the-republicans-win-the-maine-senate-race-in-2026",
      "question": "Will the Republicans win the Maine Senate race in 2026?",
      "titleZh": "the Republicans win the Maine Senate race in 2026",
      "topic": "美国政治",
      "yesPrice": 0.335,
      "noPrice": 0.665,
      "yesPct": 33.5,
      "bestBid": 0.33,
      "bestAsk": 0.34,
      "spread": 0.01,
      "volume24hr": 7825.3956499999995,
      "liquidity": 36652.4846,
      "weekChangePct": 11.0,
      "score": 37.0,
      "endDate": null,
      "icon": "https://polymarket-upload.s3.us-east-2.amazonaws.com/will-the-republican-party-control-the-senate-after-the-2026-midterm-elections-JSsqogfn0U0u.png",
      "url": "https://polymarket.com/event/will-the-republicans-win-the-maine-senate-race-in-2026",
      "nearBidDepth": 30693.18,
      "nearAskDepth": 34401.45,
      "pressureLabel": "盘口相对均衡",
      "priceDeltaSinceLastPp": 0.0,
      "bidDepthDelta": 230.79,
      "askDepthDelta": 86.52,
      "noteZh": "该事件当前 Yes 概率约 33.5%，盘口相对均衡，政治定价变化可能影响风险偏好。"
    },
    {
      "id": "616903",
      "slug": "will-1-fed-rate-cut-happen-in-2026",
      "question": "Will 1 Fed rate cut happen in 2026?",
      "titleZh": "1 美联储 rate cut happen in 2026",
      "topic": "美联储与利率",
      "yesPrice": 0.165,
      "noPrice": 0.835,
      "yesPct": 16.5,
      "bestBid": 0.16,
      "bestAsk": 0.17,
      "spread": 0.01,
      "volume24hr": 4222.754681,
      "liquidity": 37967.3316,
      "weekChangePct": -12.0,
      "score": 35.65,
      "endDate": "2026-12-31T00:00:00Z",
      "icon": "https://polymarket-upload.s3.us-east-2.amazonaws.com/how-many-fed-rate-cuts-in-2025-9qstZkSL1dn0.jpg",
      "url": "https://polymarket.com/event/will-1-fed-rate-cut-happen-in-2026",
      "nearBidDepth": 19502.33,
      "nearAskDepth": 9904.74,
      "pressureLabel": "下方承接更强",
      "priceDeltaSinceLastPp": 0.0,
      "bidDepthDelta": 400.86,
      "askDepthDelta": 705.55,
      "noteZh": "该事件当前 Yes 概率约 16.5%，下方承接更强，可映射到美债、黄金和成长股方向。"
    }
  ],
  "wallSignals": [
    {
      "id": "573655",
      "slug": "will-bitcoin-hit-150k-by-june-30-2026",
      "question": "Will Bitcoin hit $150k by June 30, 2026?",
      "titleZh": "比特币会在 2026 年 6 月 30 日前触及 15 万美元吗",
      "topic": "加密资产",
      "yesPrice": 0.0135,
      "noPrice": 0.9865,
      "yesPct": 1.4,
      "bestBid": 0.013,
      "bestAsk": 0.014,
      "spread": 0.001,
      "volume24hr": 5821652.894196,
      "liquidity": 19822.55555,
      "weekChangePct": 0.0,
      "score": 56.38,
      "endDate": "2026-07-01T04:00:00Z",
      "icon": "https://polymarket-upload.s3.us-east-2.amazonaws.com/BTC+fullsize.png",
      "url": "https://polymarket.com/event/will-bitcoin-hit-150k-by-june-30-2026",
      "nearBidDepth": 7873396.65,
      "nearAskDepth": 8942.68,
      "pressureLabel": "下方承接更强",
      "priceDeltaSinceLastPp": 0.0,
      "bidDepthDelta": 0.0,
      "askDepthDelta": 0.0,
      "noteZh": "该事件当前 Yes 概率约 1.4%，下方承接更强，更适合与 BTC / ETH 现货情绪一起看。"
    },
    {
      "id": "616912",
      "slug": "will-10-fed-rate-cuts-happen-in-2026",
      "question": "Will 10 Fed rate cuts happen in 2026?",
      "titleZh": "2026 年会出现 10 次美联储降息吗",
      "topic": "美联储与利率",
      "yesPrice": 0.0025,
      "noPrice": 0.9975,
      "yesPct": 0.2,
      "bestBid": 0.002,
      "bestAsk": 0.003,
      "spread": 0.001,
      "volume24hr": 56187.84866499998,
      "liquidity": 128097.52632,
      "weekChangePct": 0.0,
      "score": 34.03,
      "endDate": "2026-12-31T00:00:00Z",
      "icon": "https://polymarket-upload.s3.us-east-2.amazonaws.com/how-many-fed-rate-cuts-in-2025-9qstZkSL1dn0.jpg",
      "url": "https://polymarket.com/event/will-10-fed-rate-cuts-happen-in-2026",
      "nearBidDepth": 3015481.74,
      "nearAskDepth": 97754.88,
      "pressureLabel": "下方承接更强",
      "priceDeltaSinceLastPp": 0.0,
      "bidDepthDelta": 609.0,
      "askDepthDelta": 0.0,
      "noteZh": "该事件当前 Yes 概率约 0.2%，下方承接更强，可映射到美债、黄金和成长股方向。"
    },
    {
      "id": "616911",
      "slug": "will-9-fed-rate-cuts-happen-in-2026",
      "question": "Will 9 Fed rate cuts happen in 2026?",
      "titleZh": "2026 年会出现 9 次美联储降息吗",
      "topic": "美联储与利率",
      "yesPrice": 0.0025,
      "noPrice": 0.9975,
      "yesPct": 0.2,
      "bestBid": 0.002,
      "bestAsk": 0.003,
      "spread": 0.001,
      "volume24hr": 56362.491498,
      "liquidity": 129306.19585,
      "weekChangePct": 0.0,
      "score": 33.97,
      "endDate": "2026-12-31T00:00:00Z",
      "icon": "https://polymarket-upload.s3.us-east-2.amazonaws.com/how-many-fed-rate-cuts-in-2025-9qstZkSL1dn0.jpg",
      "url": "https://polymarket.com/event/will-9-fed-rate-cuts-happen-in-2026",
      "nearBidDepth": 2966151.9,
      "nearAskDepth": 96568.83,
      "pressureLabel": "下方承接更强",
      "priceDeltaSinceLastPp": 0.0,
      "bidDepthDelta": -463.0,
      "askDepthDelta": -463.0,
      "noteZh": "该事件当前 Yes 概率约 0.2%，下方承接更强，可映射到美债、黄金和成长股方向。"
    },
    {
      "id": "616910",
      "slug": "will-8-fed-rate-cuts-happen-in-2026",
      "question": "Will 8 Fed rate cuts happen in 2026?",
      "titleZh": "2026 年会出现 8 次美联储降息吗",
      "topic": "美联储与利率",
      "yesPrice": 0.0045,
      "noPrice": 0.9955,
      "yesPct": 0.4,
      "bestBid": 0.004,
      "bestAsk": 0.005,
      "spread": 0.001,
      "volume24hr": 55293.76924000001,
      "liquidity": 47761.57975,
      "weekChangePct": 0.1,
      "score": 49.94,
      "endDate": "2026-12-31T00:00:00Z",
      "icon": "https://polymarket-upload.s3.us-east-2.amazonaws.com/how-many-fed-rate-cuts-in-2025-9qstZkSL1dn0.jpg",
      "url": "https://polymarket.com/event/will-8-fed-rate-cuts-happen-in-2026",
      "nearBidDepth": 2864462.67,
      "nearAskDepth": 17561.84,
      "pressureLabel": "下方承接更强",
      "priceDeltaSinceLastPp": 0.0,
      "bidDepthDelta": -529.0,
      "askDepthDelta": -529.0,
      "noteZh": "该事件当前 Yes 概率约 0.4%，下方承接更强，可映射到美债、黄金和成长股方向。"
    },
    {
      "id": "637014",
      "slug": "will-khaled-mashal-win-the-nobel-peace-prize-in-2026-787",
      "question": "Will Khaled Mashal win the Nobel Peace Prize in 2026?",
      "titleZh": "Khaled Mashal win the Nobel Peace Prize in 2026",
      "topic": "地缘风险",
      "yesPrice": 0.006,
      "noPrice": 0.994,
      "yesPct": 0.6,
      "bestBid": 0.005,
      "bestAsk": 0.007,
      "spread": 0.002,
      "volume24hr": 9645.721259,
      "liquidity": 26688.63804,
      "weekChangePct": -0.6,
      "score": 32.65,
      "endDate": "2026-10-10T00:00:00Z",
      "icon": "https://polymarket-upload.s3.us-east-2.amazonaws.com/will-khaled-mashal-win-the-nobel-peace-prize-in-2026-OkPKZ0E4fOh9.jpg",
      "url": "https://polymarket.com/event/will-khaled-mashal-win-the-nobel-peace-prize-in-2026-787",
      "nearBidDepth": 247129.65,
      "nearAskDepth": 8919.53,
      "pressureLabel": "下方承接更强",
      "priceDeltaSinceLastPp": 0.0,
      "bidDepthDelta": 0.0,
      "askDepthDelta": -100.0,
      "noteZh": "该事件当前 Yes 概率约 0.6%，下方承接更强，适合与避险资产和地缘风险交易并看。"
    },
    {
      "id": "637005",
      "slug": "will-julian-assange-win-the-nobel-peace-prize-in-2026-899",
      "question": "Will Julian Assange win the Nobel Peace Prize in 2026?",
      "titleZh": "Julian Assange win the Nobel Peace Prize in 2026",
      "topic": "地缘风险",
      "yesPrice": 0.003,
      "noPrice": 0.997,
      "yesPct": 0.3,
      "bestBid": 0.002,
      "bestAsk": 0.004,
      "spread": 0.002,
      "volume24hr": 5731.649827000001,
      "liquidity": 36244.89426,
      "weekChangePct": -0.7,
      "score": 28.27,
      "endDate": "2026-10-10T00:00:00Z",
      "icon": "https://polymarket-upload.s3.us-east-2.amazonaws.com/will-julian-assange-win-the-nobel-peace-prize-in-2025-t2xPtLKW17Qk.png",
      "url": "https://polymarket.com/event/will-julian-assange-win-the-nobel-peace-prize-in-2026-899",
      "nearBidDepth": 251346.63,
      "nearAskDepth": 16514.21,
      "pressureLabel": "下方承接更强",
      "priceDeltaSinceLastPp": 0.0,
      "bidDepthDelta": 0.0,
      "askDepthDelta": 0.0,
      "noteZh": "该事件当前 Yes 概率约 0.3%，下方承接更强，适合与避险资产和地缘风险交易并看。"
    }
  ],
  "movers": [
    {
      "id": "573655",
      "slug": "will-bitcoin-hit-150k-by-june-30-2026",
      "question": "Will Bitcoin hit $150k by June 30, 2026?",
      "titleZh": "比特币会在 2026 年 6 月 30 日前触及 15 万美元吗",
      "topic": "加密资产",
      "yesPrice": 0.0135,
      "noPrice": 0.9865,
      "yesPct": 1.4,
      "bestBid": 0.013,
      "bestAsk": 0.014,
      "spread": 0.001,
      "volume24hr": 5821652.894196,
      "liquidity": 19822.55555,
      "weekChangePct": 0.0,
      "score": 56.38,
      "endDate": "2026-07-01T04:00:00Z",
      "icon": "https://polymarket-upload.s3.us-east-2.amazonaws.com/BTC+fullsize.png",
      "url": "https://polymarket.com/event/will-bitcoin-hit-150k-by-june-30-2026",
      "nearBidDepth": 7873396.65,
      "nearAskDepth": 8942.68,
      "pressureLabel": "下方承接更强",
      "priceDeltaSinceLastPp": 0.0,
      "bidDepthDelta": 0.0,
      "askDepthDelta": 0.0,
      "noteZh": "该事件当前 Yes 概率约 1.4%，下方承接更强，更适合与 BTC / ETH 现货情绪一起看。"
    },
    {
      "id": "616910",
      "slug": "will-8-fed-rate-cuts-happen-in-2026",
      "question": "Will 8 Fed rate cuts happen in 2026?",
      "titleZh": "2026 年会出现 8 次美联储降息吗",
      "topic": "美联储与利率",
      "yesPrice": 0.0045,
      "noPrice": 0.9955,
      "yesPct": 0.4,
      "bestBid": 0.004,
      "bestAsk": 0.005,
      "spread": 0.001,
      "volume24hr": 55293.76924000001,
      "liquidity": 47761.57975,
      "weekChangePct": 0.1,
      "score": 49.94,
      "endDate": "2026-12-31T00:00:00Z",
      "icon": "https://polymarket-upload.s3.us-east-2.amazonaws.com/how-many-fed-rate-cuts-in-2025-9qstZkSL1dn0.jpg",
      "url": "https://polymarket.com/event/will-8-fed-rate-cuts-happen-in-2026",
      "nearBidDepth": 2864462.67,
      "nearAskDepth": 17561.84,
      "pressureLabel": "下方承接更强",
      "priceDeltaSinceLastPp": 0.0,
      "bidDepthDelta": -529.0,
      "askDepthDelta": -529.0,
      "noteZh": "该事件当前 Yes 概率约 0.4%，下方承接更强，可映射到美债、黄金和成长股方向。"
    },
    {
      "id": "616902",
      "slug": "will-no-fed-rate-cuts-happen-in-2026",
      "question": "Will no Fed rate cuts happen in 2026?",
      "titleZh": "2026 年美联储会零降息吗",
      "topic": "美联储与利率",
      "yesPrice": 0.5565,
      "noPrice": 0.4435,
      "yesPct": 55.6,
      "bestBid": 0.554,
      "bestAsk": 0.559,
      "spread": 0.005,
      "volume24hr": 29747.488552999996,
      "liquidity": 81312.60534,
      "weekChangePct": 15.15,
      "score": 45.18,
      "endDate": "2026-12-31T00:00:00Z",
      "icon": "https://polymarket-upload.s3.us-east-2.amazonaws.com/how-many-fed-rate-cuts-in-2025-9qstZkSL1dn0.jpg",
      "url": "https://polymarket.com/event/will-no-fed-rate-cuts-happen-in-2026",
      "nearBidDepth": 64673.34,
      "nearAskDepth": 38211.95,
      "pressureLabel": "下方承接更强",
      "priceDeltaSinceLastPp": 0.0,
      "bidDepthDelta": 534.67,
      "askDepthDelta": 342.19,
      "noteZh": "该事件当前 Yes 概率约 55.6%，下方承接更强，可映射到美债、黄金和成长股方向。"
    },
    {
      "id": "562802",
      "slug": "will-the-democratic-party-control-the-house-after-the-2026-midterm-elections",
      "question": "Will the Democratic Party control the House after the 2026 Midterm elections?",
      "titleZh": "2026 年中期选举后，民主党会控制众议院吗",
      "topic": "美国政治",
      "yesPrice": 0.835,
      "noPrice": 0.165,
      "yesPct": 83.5,
      "bestBid": 0.83,
      "bestAsk": 0.84,
      "spread": 0.01,
      "volume24hr": 88471.439194,
      "liquidity": 109033.6847,
      "weekChangePct": -2.0,
      "score": 42.05,
      "endDate": "2026-11-03T00:00:00Z",
      "icon": "https://polymarket-upload.s3.us-east-2.amazonaws.com/will-the-democratic-party-control-the-senate-after-the-2026-midterm-elections-JJ9h02JGR09z.png",
      "url": "https://polymarket.com/event/will-the-democratic-party-control-the-house-after-the-2026-midterm-elections",
      "nearBidDepth": 22849.95,
      "nearAskDepth": 87839.24,
      "pressureLabel": "上方卖压更重",
      "priceDeltaSinceLastPp": 0.0,
      "bidDepthDelta": 0.0,
      "askDepthDelta": 19.0,
      "noteZh": "该事件当前 Yes 概率约 83.5%，上方卖压更重，政治定价变化可能影响风险偏好。"
    },
    {
      "id": "630773",
      "slug": "will-the-republicans-win-the-maine-senate-race-in-2026",
      "question": "Will the Republicans win the Maine Senate race in 2026?",
      "titleZh": "the Republicans win the Maine Senate race in 2026",
      "topic": "美国政治",
      "yesPrice": 0.335,
      "noPrice": 0.665,
      "yesPct": 33.5,
      "bestBid": 0.33,
      "bestAsk": 0.34,
      "spread": 0.01,
      "volume24hr": 7825.3956499999995,
      "liquidity": 36652.4846,
      "weekChangePct": 11.0,
      "score": 37.0,
      "endDate": null,
      "icon": "https://polymarket-upload.s3.us-east-2.amazonaws.com/will-the-republican-party-control-the-senate-after-the-2026-midterm-elections-JSsqogfn0U0u.png",
      "url": "https://polymarket.com/event/will-the-republicans-win-the-maine-senate-race-in-2026",
      "nearBidDepth": 30693.18,
      "nearAskDepth": 34401.45,
      "pressureLabel": "盘口相对均衡",
      "priceDeltaSinceLastPp": 0.0,
      "bidDepthDelta": 230.79,
      "askDepthDelta": 86.52,
      "noteZh": "该事件当前 Yes 概率约 33.5%，盘口相对均衡，政治定价变化可能影响风险偏好。"
    },
    {
      "id": "616903",
      "slug": "will-1-fed-rate-cut-happen-in-2026",
      "question": "Will 1 Fed rate cut happen in 2026?",
      "titleZh": "1 美联储 rate cut happen in 2026",
      "topic": "美联储与利率",
      "yesPrice": 0.165,
      "noPrice": 0.835,
      "yesPct": 16.5,
      "bestBid": 0.16,
      "bestAsk": 0.17,
      "spread": 0.01,
      "volume24hr": 4222.754681,
      "liquidity": 37967.3316,
      "weekChangePct": -12.0,
      "score": 35.65,
      "endDate": "2026-12-31T00:00:00Z",
      "icon": "https://polymarket-upload.s3.us-east-2.amazonaws.com/how-many-fed-rate-cuts-in-2025-9qstZkSL1dn0.jpg",
      "url": "https://polymarket.com/event/will-1-fed-rate-cut-happen-in-2026",
      "nearBidDepth": 19502.33,
      "nearAskDepth": 9904.74,
      "pressureLabel": "下方承接更强",
      "priceDeltaSinceLastPp": 0.0,
      "bidDepthDelta": 400.86,
      "askDepthDelta": 705.55,
      "noteZh": "该事件当前 Yes 概率约 16.5%，下方承接更强，可映射到美债、黄金和成长股方向。"
    }
  ],
  "topicSummary": [
    {
      "topic": "地缘风险",
      "count": 20,
      "avgYesPct": 3.5,
      "hotestTitle": "Khaled Mashal win the Nobel Peace Prize in 2026"
    },
    {
      "topic": "美国政治",
      "count": 15,
      "avgYesPct": 34.9,
      "hotestTitle": "2026 年中期选举后，民主党会控制众议院吗"
    },
    {
      "topic": "美联储与利率",
      "count": 13,
      "avgYesPct": 7.3,
      "hotestTitle": "2026 年会出现 8 次美联储降息吗"
    },
    {
      "topic": "加密资产",
      "count": 2,
      "avgYesPct": 5.5,
      "hotestTitle": "比特币会在 2026 年 6 月 30 日前触及 15 万美元吗"
    },
    {
      "topic": "宏观数据",
      "count": 1,
      "avgYesPct": 25.0,
      "hotestTitle": "美国会在 2026 年底前陷入衰退吗"
    }
  ],
  "markets": [
    {
      "id": "573655",
      "slug": "will-bitcoin-hit-150k-by-june-30-2026",
      "question": "Will Bitcoin hit $150k by June 30, 2026?",
      "titleZh": "比特币会在 2026 年 6 月 30 日前触及 15 万美元吗",
      "topic": "加密资产",
      "yesPrice": 0.0135,
      "noPrice": 0.9865,
      "yesPct": 1.4,
      "bestBid": 0.013,
      "bestAsk": 0.014,
      "spread": 0.001,
      "volume24hr": 5821652.894196,
      "liquidity": 19822.55555,
      "weekChangePct": 0.0,
      "score": 56.38,
      "endDate": "2026-07-01T04:00:00Z",
      "icon": "https://polymarket-upload.s3.us-east-2.amazonaws.com/BTC+fullsize.png",
      "url": "https://polymarket.com/event/will-bitcoin-hit-150k-by-june-30-2026",
      "nearBidDepth": 7873396.65,
      "nearAskDepth": 8942.68,
      "pressureLabel": "下方承接更强",
      "priceDeltaSinceLastPp": 0.0,
      "bidDepthDelta": 0.0,
      "askDepthDelta": 0.0,
      "noteZh": "该事件当前 Yes 概率约 1.4%，下方承接更强，更适合与 BTC / ETH 现货情绪一起看。"
    },
    {
      "id": "616910",
      "slug": "will-8-fed-rate-cuts-happen-in-2026",
      "question": "Will 8 Fed rate cuts happen in 2026?",
      "titleZh": "2026 年会出现 8 次美联储降息吗",
      "topic": "美联储与利率",
      "yesPrice": 0.0045,
      "noPrice": 0.9955,
      "yesPct": 0.4,
      "bestBid": 0.004,
      "bestAsk": 0.005,
      "spread": 0.001,
      "volume24hr": 55293.76924000001,
      "liquidity": 47761.57975,
      "weekChangePct": 0.1,
      "score": 49.94,
      "endDate": "2026-12-31T00:00:00Z",
      "icon": "https://polymarket-upload.s3.us-east-2.amazonaws.com/how-many-fed-rate-cuts-in-2025-9qstZkSL1dn0.jpg",
      "url": "https://polymarket.com/event/will-8-fed-rate-cuts-happen-in-2026",
      "nearBidDepth": 2864462.67,
      "nearAskDepth": 17561.84,
      "pressureLabel": "下方承接更强",
      "priceDeltaSinceLastPp": 0.0,
      "bidDepthDelta": -529.0,
      "askDepthDelta": -529.0,
      "noteZh": "该事件当前 Yes 概率约 0.4%，下方承接更强，可映射到美债、黄金和成长股方向。"
    },
    {
      "id": "616902",
      "slug": "will-no-fed-rate-cuts-happen-in-2026",
      "question": "Will no Fed rate cuts happen in 2026?",
      "titleZh": "2026 年美联储会零降息吗",
      "topic": "美联储与利率",
      "yesPrice": 0.5565,
      "noPrice": 0.4435,
      "yesPct": 55.6,
      "bestBid": 0.554,
      "bestAsk": 0.559,
      "spread": 0.005,
      "volume24hr": 29747.488552999996,
      "liquidity": 81312.60534,
      "weekChangePct": 15.15,
      "score": 45.18,
      "endDate": "2026-12-31T00:00:00Z",
      "icon": "https://polymarket-upload.s3.us-east-2.amazonaws.com/how-many-fed-rate-cuts-in-2025-9qstZkSL1dn0.jpg",
      "url": "https://polymarket.com/event/will-no-fed-rate-cuts-happen-in-2026",
      "nearBidDepth": 64673.34,
      "nearAskDepth": 38211.95,
      "pressureLabel": "下方承接更强",
      "priceDeltaSinceLastPp": 0.0,
      "bidDepthDelta": 534.67,
      "askDepthDelta": 342.19,
      "noteZh": "该事件当前 Yes 概率约 55.6%，下方承接更强，可映射到美债、黄金和成长股方向。"
    },
    {
      "id": "562802",
      "slug": "will-the-democratic-party-control-the-house-after-the-2026-midterm-elections",
      "question": "Will the Democratic Party control the House after the 2026 Midterm elections?",
      "titleZh": "2026 年中期选举后，民主党会控制众议院吗",
      "topic": "美国政治",
      "yesPrice": 0.835,
      "noPrice": 0.165,
      "yesPct": 83.5,
      "bestBid": 0.83,
      "bestAsk": 0.84,
      "spread": 0.01,
      "volume24hr": 88471.439194,
      "liquidity": 109033.6847,
      "weekChangePct": -2.0,
      "score": 42.05,
      "endDate": "2026-11-03T00:00:00Z",
      "icon": "https://polymarket-upload.s3.us-east-2.amazonaws.com/will-the-democratic-party-control-the-senate-after-the-2026-midterm-elections-JJ9h02JGR09z.png",
      "url": "https://polymarket.com/event/will-the-democratic-party-control-the-house-after-the-2026-midterm-elections",
      "nearBidDepth": 22849.95,
      "nearAskDepth": 87839.24,
      "pressureLabel": "上方卖压更重",
      "priceDeltaSinceLastPp": 0.0,
      "bidDepthDelta": 0.0,
      "askDepthDelta": 19.0,
      "noteZh": "该事件当前 Yes 概率约 83.5%，上方卖压更重，政治定价变化可能影响风险偏好。"
    },
    {
      "id": "630773",
      "slug": "will-the-republicans-win-the-maine-senate-race-in-2026",
      "question": "Will the Republicans win the Maine Senate race in 2026?",
      "titleZh": "the Republicans win the Maine Senate race in 2026",
      "topic": "美国政治",
      "yesPrice": 0.335,
      "noPrice": 0.665,
      "yesPct": 33.5,
      "bestBid": 0.33,
      "bestAsk": 0.34,
      "spread": 0.01,
      "volume24hr": 7825.3956499999995,
      "liquidity": 36652.4846,
      "weekChangePct": 11.0,
      "score": 37.0,
      "endDate": null,
      "icon": "https://polymarket-upload.s3.us-east-2.amazonaws.com/will-the-republican-party-control-the-senate-after-the-2026-midterm-elections-JSsqogfn0U0u.png",
      "url": "https://polymarket.com/event/will-the-republicans-win-the-maine-senate-race-in-2026",
      "nearBidDepth": 30693.18,
      "nearAskDepth": 34401.45,
      "pressureLabel": "盘口相对均衡",
      "priceDeltaSinceLastPp": 0.0,
      "bidDepthDelta": 230.79,
      "askDepthDelta": 86.52,
      "noteZh": "该事件当前 Yes 概率约 33.5%，盘口相对均衡，政治定价变化可能影响风险偏好。"
    },
    {
      "id": "616903",
      "slug": "will-1-fed-rate-cut-happen-in-2026",
      "question": "Will 1 Fed rate cut happen in 2026?",
      "titleZh": "1 美联储 rate cut happen in 2026",
      "topic": "美联储与利率",
      "yesPrice": 0.165,
      "noPrice": 0.835,
      "yesPct": 16.5,
      "bestBid": 0.16,
      "bestAsk": 0.17,
      "spread": 0.01,
      "volume24hr": 4222.754681,
      "liquidity": 37967.3316,
      "weekChangePct": -12.0,
      "score": 35.65,
      "endDate": "2026-12-31T00:00:00Z",
      "icon": "https://polymarket-upload.s3.us-east-2.amazonaws.com/how-many-fed-rate-cuts-in-2025-9qstZkSL1dn0.jpg",
      "url": "https://polymarket.com/event/will-1-fed-rate-cut-happen-in-2026",
      "nearBidDepth": 19502.33,
      "nearAskDepth": 9904.74,
      "pressureLabel": "下方承接更强",
      "priceDeltaSinceLastPp": 0.0,
      "bidDepthDelta": 400.86,
      "askDepthDelta": 705.55,
      "noteZh": "该事件当前 Yes 概率约 16.5%，下方承接更强，可映射到美债、黄金和成长股方向。"
    },
    {
      "id": "616912",
      "slug": "will-10-fed-rate-cuts-happen-in-2026",
      "question": "Will 10 Fed rate cuts happen in 2026?",
      "titleZh": "2026 年会出现 10 次美联储降息吗",
      "topic": "美联储与利率",
      "yesPrice": 0.0025,
      "noPrice": 0.9975,
      "yesPct": 0.2,
      "bestBid": 0.002,
      "bestAsk": 0.003,
      "spread": 0.001,
      "volume24hr": 56187.84866499998,
      "liquidity": 128097.52632,
      "weekChangePct": 0.0,
      "score": 34.03,
      "endDate": "2026-12-31T00:00:00Z",
      "icon": "https://polymarket-upload.s3.us-east-2.amazonaws.com/how-many-fed-rate-cuts-in-2025-9qstZkSL1dn0.jpg",
      "url": "https://polymarket.com/event/will-10-fed-rate-cuts-happen-in-2026",
      "nearBidDepth": 3015481.74,
      "nearAskDepth": 97754.88,
      "pressureLabel": "下方承接更强",
      "priceDeltaSinceLastPp": 0.0,
      "bidDepthDelta": 609.0,
      "askDepthDelta": 0.0,
      "noteZh": "该事件当前 Yes 概率约 0.2%，下方承接更强，可映射到美债、黄金和成长股方向。"
    },
    {
      "id": "616911",
      "slug": "will-9-fed-rate-cuts-happen-in-2026",
      "question": "Will 9 Fed rate cuts happen in 2026?",
      "titleZh": "2026 年会出现 9 次美联储降息吗",
      "topic": "美联储与利率",
      "yesPrice": 0.0025,
      "noPrice": 0.9975,
      "yesPct": 0.2,
      "bestBid": 0.002,
      "bestAsk": 0.003,
      "spread": 0.001,
      "volume24hr": 56362.491498,
      "liquidity": 129306.19585,
      "weekChangePct": 0.0,
      "score": 33.97,
      "endDate": "2026-12-31T00:00:00Z",
      "icon": "https://polymarket-upload.s3.us-east-2.amazonaws.com/how-many-fed-rate-cuts-in-2025-9qstZkSL1dn0.jpg",
      "url": "https://polymarket.com/event/will-9-fed-rate-cuts-happen-in-2026",
      "nearBidDepth": 2966151.9,
      "nearAskDepth": 96568.83,
      "pressureLabel": "下方承接更强",
      "priceDeltaSinceLastPp": 0.0,
      "bidDepthDelta": -463.0,
      "askDepthDelta": -463.0,
      "noteZh": "该事件当前 Yes 概率约 0.2%，下方承接更强，可映射到美债、黄金和成长股方向。"
    },
    {
      "id": "637014",
      "slug": "will-khaled-mashal-win-the-nobel-peace-prize-in-2026-787",
      "question": "Will Khaled Mashal win the Nobel Peace Prize in 2026?",
      "titleZh": "Khaled Mashal win the Nobel Peace Prize in 2026",
      "topic": "地缘风险",
      "yesPrice": 0.006,
      "noPrice": 0.994,
      "yesPct": 0.6,
      "bestBid": 0.005,
      "bestAsk": 0.007,
      "spread": 0.002,
      "volume24hr": 9645.721259,
      "liquidity": 26688.63804,
      "weekChangePct": -0.6,
      "score": 32.65,
      "endDate": "2026-10-10T00:00:00Z",
      "icon": "https://polymarket-upload.s3.us-east-2.amazonaws.com/will-khaled-mashal-win-the-nobel-peace-prize-in-2026-OkPKZ0E4fOh9.jpg",
      "url": "https://polymarket.com/event/will-khaled-mashal-win-the-nobel-peace-prize-in-2026-787",
      "nearBidDepth": 247129.65,
      "nearAskDepth": 8919.53,
      "pressureLabel": "下方承接更强",
      "priceDeltaSinceLastPp": 0.0,
      "bidDepthDelta": 0.0,
      "askDepthDelta": -100.0,
      "noteZh": "该事件当前 Yes 概率约 0.6%，下方承接更强，适合与避险资产和地缘风险交易并看。"
    },
    {
      "id": "630772",
      "slug": "will-the-democrats-win-the-maine-senate-race-in-2026",
      "question": "Will the Democrats win the Maine Senate race in 2026?",
      "titleZh": "the Democrats win the Maine Senate race in 2026",
      "topic": "美国政治",
      "yesPrice": 0.675,
      "noPrice": 0.325,
      "yesPct": 67.5,
      "bestBid": 0.67,
      "bestAsk": 0.68,
      "spread": 0.01,
      "volume24hr": 4642.9056359999995,
      "liquidity": 59631.1844,
      "weekChangePct": -9.0,
      "score": 32.21,
      "endDate": null,
      "icon": "https://polymarket-upload.s3.us-east-2.amazonaws.com/will-the-democratic-party-control-the-senate-after-the-2026-midterm-elections-JJ9h02JGR09z.png",
      "url": "https://polymarket.com/event/will-the-democrats-win-the-maine-senate-race-in-2026",
      "nearBidDepth": 57140.36,
      "nearAskDepth": 55360.72,
      "pressureLabel": "盘口相对均衡",
      "priceDeltaSinceLastPp": 0.0,
      "bidDepthDelta": -255.0,
      "askDepthDelta": 1148.15,
      "noteZh": "该事件当前 Yes 概率约 67.5%，盘口相对均衡，政治定价变化可能影响风险偏好。"
    },
    {
      "id": "562831",
      "slug": "2026-balance-of-power-r-senate-r-house-537",
      "question": "2026 Balance of Power: R Senate, R House",
      "titleZh": "2026 年权力格局：共和党参议院 + 共和党众议院",
      "topic": "美国政治",
      "yesPrice": 0.155,
      "noPrice": 0.845,
      "yesPct": 15.5,
      "bestBid": 0.15,
      "bestAsk": 0.16,
      "spread": 0.01,
      "volume24hr": 26556.9924,
      "liquidity": 90974.5512,
      "weekChangePct": 3.0,
      "score": 31.52,
      "endDate": "2026-11-03T00:00:00Z",
      "icon": "https://polymarket-upload.s3.us-east-2.amazonaws.com/balance-of-power-2024-election-r-Fp-y4ONJBS.jpg",
      "url": "https://polymarket.com/event/2026-balance-of-power-r-senate-r-house-537",
      "nearBidDepth": 53119.95,
      "nearAskDepth": 23799.05,
      "pressureLabel": "下方承接更强",
      "priceDeltaSinceLastPp": 0.0,
      "bidDepthDelta": -1.18,
      "askDepthDelta": 0.0,
      "noteZh": "该事件当前 Yes 概率约 15.5%，下方承接更强，政治定价变化可能影响风险偏好。"
    },
    {
      "id": "562803",
      "slug": "will-the-republican-party-control-the-house-after-the-2026-midterm-elections",
      "question": "Will the Republican Party control the House after the 2026 Midterm elections?",
      "titleZh": "2026 年中期选举后，共和党会控制众议院吗",
      "topic": "美国政治",
      "yesPrice": 0.165,
      "noPrice": 0.835,
      "yesPct": 16.5,
      "bestBid": 0.16,
      "bestAsk": 0.17,
      "spread": 0.01,
      "volume24hr": 33986.178337000005,
      "liquidity": 112190.5057,
      "weekChangePct": 2.0,
      "score": 30.86,
      "endDate": "2026-11-03T00:00:00Z",
      "icon": "https://polymarket-upload.s3.us-east-2.amazonaws.com/will-the-republican-party-control-the-senate-after-the-2026-midterm-elections-JSsqogfn0U0u.png",
      "url": "https://polymarket.com/event/will-the-republican-party-control-the-house-after-the-2026-midterm-elections",
      "nearBidDepth": 115657.74,
      "nearAskDepth": 28188.46,
      "pressureLabel": "下方承接更强",
      "priceDeltaSinceLastPp": 0.0,
      "bidDepthDelta": 0.0,
      "askDepthDelta": 6.0,
      "noteZh": "该事件当前 Yes 概率约 16.5%，下方承接更强，政治定价变化可能影响风险偏好。"
    },
    {
      "id": "637010",
      "slug": "will-antnio-guterres-win-the-nobel-peace-prize-in-2026-623",
      "question": "Will António Guterres win the Nobel Peace Prize in 2026?",
      "titleZh": "António Guterres win the Nobel Peace Prize in 2026",
      "topic": "地缘风险",
      "yesPrice": 0.004,
      "noPrice": 0.996,
      "yesPct": 0.4,
      "bestBid": 0.003,
      "bestAsk": 0.005,
      "spread": 0.002,
      "volume24hr": 6473.102989999997,
      "liquidity": 28521.81122,
      "weekChangePct": -0.4,
      "score": 29.51,
      "endDate": "2026-10-10T00:00:00Z",
      "icon": "https://polymarket-upload.s3.us-east-2.amazonaws.com/will-antnio-guterres-win-the-nobel-peace-prize-in-2025-vGiiiNU6gBET.jpg",
      "url": "https://polymarket.com/event/will-antnio-guterres-win-the-nobel-peace-prize-in-2026-623",
      "nearBidDepth": 222377.01,
      "nearAskDepth": 11347.88,
      "pressureLabel": "下方承接更强",
      "priceDeltaSinceLastPp": 0.0,
      "bidDepthDelta": -0.0,
      "askDepthDelta": 0.0,
      "noteZh": "该事件当前 Yes 概率约 0.4%，下方承接更强，适合与避险资产和地缘风险交易并看。"
    },
    {
      "id": "637016",
      "slug": "will-recep-tayyip-erdoan-win-the-nobel-peace-prize-in-2026",
      "question": "Will Recep Tayyip Erdoğan win the Nobel Peace Prize in 2026?",
      "titleZh": "Recep Tayyip Erdoğan win the Nobel Peace Prize in 2026",
      "topic": "地缘风险",
      "yesPrice": 0.0055,
      "noPrice": 0.9945,
      "yesPct": 0.5,
      "bestBid": 0.004,
      "bestAsk": 0.007,
      "spread": 0.003,
      "volume24hr": 6512.452510000003,
      "liquidity": 31939.76786,
      "weekChangePct": -1.05,
      "score": 29.37,
      "endDate": "2026-10-10T00:00:00Z",
      "icon": "https://polymarket-upload.s3.us-east-2.amazonaws.com/will-recep-tayyip-erdoan-win-the-nobel-peace-prize-in-2026-Jm-M0cEVdnrc.jpg",
      "url": "https://polymarket.com/event/will-recep-tayyip-erdoan-win-the-nobel-peace-prize-in-2026",
      "nearBidDepth": 236252.8,
      "nearAskDepth": 15157.11,
      "pressureLabel": "下方承接更强",
      "priceDeltaSinceLastPp": 0.0,
      "bidDepthDelta": 0.0,
      "askDepthDelta": 0.0,
      "noteZh": "该事件当前 Yes 概率约 0.5%，下方承接更强，适合与避险资产和地缘风险交易并看。"
    },
    {
      "id": "637005",
      "slug": "will-julian-assange-win-the-nobel-peace-prize-in-2026-899",
      "question": "Will Julian Assange win the Nobel Peace Prize in 2026?",
      "titleZh": "Julian Assange win the Nobel Peace Prize in 2026",
      "topic": "地缘风险",
      "yesPrice": 0.003,
      "noPrice": 0.997,
      "yesPct": 0.3,
      "bestBid": 0.002,
      "bestAsk": 0.004,
      "spread": 0.002,
      "volume24hr": 5731.649827000001,
      "liquidity": 36244.89426,
      "weekChangePct": -0.7,
      "score": 28.27,
      "endDate": "2026-10-10T00:00:00Z",
      "icon": "https://polymarket-upload.s3.us-east-2.amazonaws.com/will-julian-assange-win-the-nobel-peace-prize-in-2025-t2xPtLKW17Qk.png",
      "url": "https://polymarket.com/event/will-julian-assange-win-the-nobel-peace-prize-in-2026-899",
      "nearBidDepth": 251346.63,
      "nearAskDepth": 16514.21,
      "pressureLabel": "下方承接更强",
      "priceDeltaSinceLastPp": 0.0,
      "bidDepthDelta": 0.0,
      "askDepthDelta": 0.0,
      "noteZh": "该事件当前 Yes 概率约 0.3%，下方承接更强，适合与避险资产和地缘风险交易并看。"
    },
    {
      "id": "609655",
      "slug": "us-recession-by-end-of-2026",
      "question": "US recession by end of 2026?",
      "titleZh": "美国会在 2026 年底前陷入衰退吗",
      "topic": "宏观数据",
      "yesPrice": 0.25,
      "noPrice": 0.75,
      "yesPct": 25.0,
      "bestBid": 0.24,
      "bestAsk": 0.26,
      "spread": 0.02,
      "volume24hr": 4213.689698,
      "liquidity": 29371.0123,
      "weekChangePct": -0.5,
      "score": 23.81,
      "endDate": "2027-01-31T00:00:00Z",
      "icon": "https://polymarket-upload.s3.us-east-2.amazonaws.com/us-recession-in-2025-01ZjnLjvO4a3.jpg",
      "url": "https://polymarket.com/event/us-recession-by-end-of-2026",
      "nearBidDepth": 3774.65,
      "nearAskDepth": 4071.98,
      "pressureLabel": "盘口相对均衡",
      "priceDeltaSinceLastPp": 0.0,
      "bidDepthDelta": 5.0,
      "askDepthDelta": 0.0,
      "noteZh": "该事件当前 Yes 概率约 25.0%，盘口相对均衡，更适合放进宏观节奏与风险偏好框架里解读。"
    },
    {
      "id": "573656",
      "slug": "will-bitcoin-hit-150k-by-december-31-2026",
      "question": "Will Bitcoin hit $150k by December 31, 2026?",
      "titleZh": "比特币会在 2026 年 12 月 31 日前触及 15 万美元吗",
      "topic": "加密资产",
      "yesPrice": 0.095,
      "noPrice": 0.905,
      "yesPct": 9.5,
      "bestBid": 0.09,
      "bestAsk": 0.1,
      "spread": 0.01,
      "volume24hr": 290.659889,
      "liquidity": 30019.8616,
      "weekChangePct": 0.0,
      "score": 19.4,
      "endDate": "2027-01-01T04:00:00Z",
      "icon": "https://polymarket-upload.s3.us-east-2.amazonaws.com/BTC+fullsize.png",
      "url": "https://polymarket.com/event/will-bitcoin-hit-150k-by-december-31-2026",
      "nearBidDepth": 11784.91,
      "nearAskDepth": 7392.8,
      "pressureLabel": "盘口相对均衡",
      "priceDeltaSinceLastPp": 0.0,
      "bidDepthDelta": 0.0,
      "askDepthDelta": 0.0,
      "noteZh": "该事件当前 Yes 概率约 9.5%，盘口相对均衡，更适合与 BTC / ETH 现货情绪一起看。"
    }
  ]
}